jianpian_downloader/__init__.py
jianpian_downloader/movie_downloader.py
jianpian_downloader-1.0.3.dist-info/LICENSE
jianpian_downloader-1.0.3.dist-info/METADATA
jianpian_downloader-1.0.3.dist-info/WHEEL
jianpian_downloader-1.0.3.dist-info/entry_points.txt
jianpian_downloader-1.0.3.dist-info/top_level.txt
jianpian_downloader-1.0.3.dist-info/RECORD
