Metadata-Version: 2.1
Name: jianpian-downloader
Version: 1.0.3
Summary: 一个优雅的视频下载工具
Home-page: https://github.com/skyfireitdiy/JianpianDownloader
Author: skyfireitdiy
Author-email: skyfireitdiy@hotmail.com
Classifier: Programming Language :: Python :: 3
Classifier: Programming Language :: Python :: 3.7
Classifier: Programming Language :: Python :: 3.8
Classifier: Programming Language :: Python :: 3.9
Classifier: Programming Language :: Python :: 3.10
Classifier: License :: OSI Approved :: MIT License
Classifier: Operating System :: OS Independent
Classifier: Environment :: Console
Classifier: Topic :: Internet :: WWW/HTTP :: Browsers
Classifier: Topic :: Multimedia :: Video
Requires-Python: >=3.7
License-File: LICENSE
Requires-Dist: requests>=2.31.0
Requires-Dist: beautifulsoup4>=4.12.0
Requires-Dist: m3u8>=3.6.0
Requires-Dist: rich>=13.7.0
Requires-Dist: tqdm>=4.66.0
